detectorusoutlierus/__init__.py
detectorusoutlierus/outliers.py
detectorusoutlierus-0.0.1.dist-info/LICENSE
detectorusoutlierus-0.0.1.dist-info/METADATA
detectorusoutlierus-0.0.1.dist-info/WHEEL
detectorusoutlierus-0.0.1.dist-info/top_level.txt
detectorusoutlierus-0.0.1.dist-info/RECORD
