Metadata-Version: 2.1
Name: detectorusoutlierus
Version: 0.0.1
Summary: Small package created for detecting outliers
Author-email: Artorius <Artorius.81@yandex.ru>
Project-URL: Homepage, https://github.com/Artorius81
Classifier: Programming Language :: Python :: 3
Classifier: License :: OSI Approved :: MIT License
Classifier: Operating System :: OS Independent
Requires-Python: >=3.7
License-File: LICENSE
